mongobj/__init__.py
mongobj/document.py
mongobj/document_manager.py
mongobj-1.0.1.dist-info/METADATA
mongobj-1.0.1.dist-info/RECORD
mongobj-1.0.1.dist-info/WHEEL
mongobj-1.0.1.dist-info/top_level.txt
mongobj-1.0.1.dist-info/zip-safe
